CHANGES.rst
LICENSE.txt
MANIFEST.in
README.rst
setup.py
src/bst/__init__.py
src/bst.pygasus.security.egg-info/PKG-INFO
src/bst.pygasus.security.egg-info/SOURCES.txt
src/bst.pygasus.security.egg-info/dependency_links.txt
src/bst.pygasus.security.egg-info/entry_points.txt
src/bst.pygasus.security.egg-info/namespace_packages.txt
src/bst.pygasus.security.egg-info/not-zip-safe
src/bst.pygasus.security.egg-info/requires.txt
src/bst.pygasus.security.egg-info/top_level.txt
src/bst/pygasus/__init__.py
src/bst/pygasus/security/__init__.py
src/bst/pygasus/security/auth.zcml
src/bst/pygasus/security/configure.zcml
src/bst/pygasus/security/extjs.py
src/bst/pygasus/security/interaction.py
src/bst/pygasus/security/interfaces.py
src/bst/pygasus/security/pluggableauth.py
src/bst/pygasus/security/plugins.py
src/bst/pygasus/security/principal.py
src/bst/pygasus/security/applogin/Controller.js
src/bst/pygasus/security/applogin/LoginView.js
src/bst/pygasus/security/applogin/application.js
src/bst/pygasus/security/applogin/resources/key.png
src/bst/pygasus/security/applogin/resources/login_icon.png
src/bst/pygasus/security/applogin/resources/style.css
src/bst/pygasus/security/locales/bb.extjs.security.pot
src/bst/pygasus/security/locales/de/LC_MESSAGES/bst.pygasus.security.po
src/bst/pygasus/security/locales/fr/LC_MESSAGES/bst.pygasus.security.po